README
setup.py
uaiohttpclient.py
micropython_uaiohttpclient.egg-info/PKG-INFO
micropython_uaiohttpclient.egg-info/SOURCES.txt
micropython_uaiohttpclient.egg-info/dependency_links.txt
micropython_uaiohttpclient.egg-info/top_level.txt