Metadata-Version: 1.0
Name: micropython-uaiohttpclient
Version: 0.5.1
Summary: HTTP client module for MicroPython uasyncio module
Home-page: https://github.com/micropython/micropython-lib
Author: micropython-lib Developers
Author-email: micro-python@googlegroups.com
License: MIT
Platform: UNKNOWN
